accp/__init__.py
accp/__main__.py
accp/caption.py
accp/utils/__init__.py
accp/utils/infolog.py
accp/utils/plot.py
accp-0.0.1.dist-info/METADATA
accp-0.0.1.dist-info/RECORD
accp-0.0.1.dist-info/WHEEL
accp-0.0.1.dist-info/top_level.txt
