Metadata-Version: 2.1
Name: accp
Version: 0.0.1
Summary: A pakage for crawling and processing audio, caption from Youtube
Home-page: https://github.com/zldzmfoq12/aud_crawler
Author: Seugnhun Jeong
Author-email: zldzmfoq12@naver.com
License: UNKNOWN
Download-URL: https://github.com/zldzmfoq12/aud_crawler/archive/0.0.tar.gz
Keywords: aud_crawler
Platform: UNKNOWN
Classifier: Programming Language :: Python :: 3
Classifier: License :: OSI Approved :: MIT License
Classifier: Operating System :: OS Independent
Requires-Python: >=3.6
